Metadata-Version: 2.1
Name: gdir
Version: 0.3.0
Summary: Command line tool which queries Google Directions. Displays results as human-readable text.
Home-page: https://github.com/pafoster/gdir
Author: Peter Foster
Author-email: pyitlib@gmx.us
License: MIT
Download-URL: https://github.com/pafoster/gdir/archive/0.3.0.tar.gz
Keywords: Google Directions,Google Maps,command line,terminal,public transport,transit,directions
Platform: UNKNOWN
Classifier: Development Status :: 4 - Beta
Classifier: Environment :: Console
Classifier: Intended Audience :: End Users/Desktop
Classifier: License :: OSI Approved :: MIT License
Classifier: Natural Language :: English
Classifier: Programming Language :: Python :: 3
Classifier: Topic :: Utilities 
Requires-Python: >=3
License-File: LICENSE
